ananimlib/__init__.py
ananimlib/ananim.py
ananimlib/ananim_old.py
ananimlib/anobject.py
ananimlib/anobject_dead.py
ananimlib/backend.py
ananimlib/basic_instructions.py
ananimlib/bezier.py
ananimlib/camera.py
ananimlib/common_anobs.py
ananimlib/config.py
ananimlib/coordinates.py
ananimlib/core_instructions.py
ananimlib/core_instructions_old.py
ananimlib/experimental_anobjects.py
ananimlib/instruction.py
ananimlib/plot_anobject.py
ananimlib/plot_anobs.py
ananimlib/render.py
ananimlib/scene.py
ananimlib/search.py
ananimlib/tex_anobject.py
ananimlib/transfer_funcs.py
ananimlib-0.0.1.1.dist-info/METADATA
ananimlib-0.0.1.1.dist-info/WHEEL
ananimlib-0.0.1.1.dist-info/quickstart_ex1.gif
ananimlib-0.0.1.1.dist-info/top_level.txt
ananimlib-0.0.1.1.dist-info/RECORD
