Metadata-Version: 2.1
Name: ananimlib
Version: 0.0.1.1
Summary: Mathematically Precise Animations, Intuitive and Extensible API
Home-page: https://github.com/gtruch/ananimlib
Author: G. Ruch
Author-email: gtruch@stthomas.edu
License: UNKNOWN
Project-URL: Bug Tracker, https://github.com/gtruch/ananimlib
Platform: UNKNOWN
Classifier: Programming Language :: Python :: 3
Classifier: Operating System :: OS Independent
Requires-Dist: pycairo
Requires-Dist: colour
Requires-Dist: pydub
Requires-Dist: pygame
Requires-Dist: pillow
Requires-Dist: numpy
Requires-Dist: scipy
